{
    "type": "Journal Article",
    "doi": "10.1007/s10055-025-01149-6",
    "bibtex": "lunding2025arthur",
    "sort": 202501,
    "year": 2025,
    "month": 1,
    "title": "ARTHUR: Authoring Human-Robot Collaboration Processes with Augmented Reality using Hybrid User Interfaces",
    "authors": [
        { "first": "Rasmus", "last": "Lunding" },
        { "first": "Sebastian", "last": "Hubenschmid" },
        { "first": "Tiare", "last": "Feuchtner" },
        { "first": "Kaj", "last": "Grønbæk" }
    ],
    "conference": "Springer VR'25",
    "conference_short": "",
    "journal": "TODO",
    "journal_short": "TODO",
    "links": [
        {
            "name": "PDF",
            "type": "pdf",
            "url": "/publications/lunding2025arthur.pdf"
        },
        {
            "name": "Video",
            "type": "video",
            "url": "https://www.youtube.com/playlist?list=PLhjFAueqW0cuRR-ZruATwfFXfasdi5Gli"
        },
        {
            "name": "Code",
            "type": "code",
            "url": "https://gitlab.au.dk/arthur"
        }
    ]
}


